py2terraform/__init__.py
py2terraform/helpers.py
py2terraform/types.py
py2terraform/blocks/__init__.py
py2terraform/blocks/locals.py
py2terraform/blocks/module.py
py2terraform/blocks/provider.py
py2terraform/blocks/resource.py
py2terraform/blocks/terraform.py
py2terraform/blocks/variable.py
py2terraform-0.3.0.dist-info/LICENSE
py2terraform-0.3.0.dist-info/METADATA
py2terraform-0.3.0.dist-info/WHEEL
py2terraform-0.3.0.dist-info/top_level.txt
py2terraform-0.3.0.dist-info/RECORD
