Metadata-Version: 2.1
Name: py2terraform
Version: 0.3.0
License-File: LICENSE
